commutil/__init__.py
commutil/common_imports.py
commutil/constants/__init__.py
commutil/constants/colors.py
commutil/constants/config.py
commutil/utils/__init__.py
commutil/utils/convert_util.py
commutil/utils/debug_util.py
commutil/utils/import_util.py
commutil/utils/llm_util.py
commutil/utils/log_util.py
commutil/utils/loguru_util.py
commutil/utils/openai_util.py
commutil/utils/run_util.py
commutil/utils/statistic_util.py
commutil/utils/string_util.py
commutil/utils/structs_util.py
commutil/utils/time_util.py
commutil-0.0.6.dist-info/licenses/LICENSE
commutil-0.0.6.dist-info/METADATA
commutil-0.0.6.dist-info/WHEEL
commutil-0.0.6.dist-info/top_level.txt
commutil-0.0.6.dist-info/RECORD
