Metadata-Version: 2.4
Name: commutil
Version: 0.0.6
Summary: A common utilities package
Author-email: noname <noname@no.com>
Classifier: Programming Language :: Python :: 3
Classifier: License :: OSI Approved :: MIT License
Classifier: Operating System :: OS Independent
Requires-Python: >=3.6
License-File: LICENSE
Dynamic: license-file
